pycoral/__init__.py
pycoral/pycoral.py
pycoral-0.2.0.dist-info/LICENSE
pycoral-0.2.0.dist-info/METADATA
pycoral-0.2.0.dist-info/WHEEL
pycoral-0.2.0.dist-info/entry_points.txt
pycoral-0.2.0.dist-info/top_level.txt
pycoral-0.2.0.dist-info/RECORD
