Metadata-Version: 2.1
Name: pycoral
Version: 0.2.0
Summary: Simple CLI for Allen Coral Atlas
Author: Samapriya Roy
Author-email: samapriya.roy@gmail.com
License: MIT
Classifier: Intended Audience :: Developers
Classifier: Intended Audience :: Science/Research
Classifier: Natural Language :: English
Classifier: License :: OSI Approved :: MIT License
Classifier: Programming Language :: Python :: 3.6
Classifier: Programming Language :: Python :: 3.7
Classifier: Operating System :: OS Independent
Classifier: Topic :: Scientific/Engineering :: GIS
License-File: LICENSE
